itkwasm_image_io_wasi/__init__.py
itkwasm_image_io_wasi/_version.py
itkwasm_image_io_wasi/bio_rad_read_image.py
itkwasm_image_io_wasi/bio_rad_write_image.py
itkwasm_image_io_wasi/bmp_read_image.py
itkwasm_image_io_wasi/bmp_write_image.py
itkwasm_image_io_wasi/extension_to_image_io.py
itkwasm_image_io_wasi/fdf_read_image.py
itkwasm_image_io_wasi/fdf_write_image.py
itkwasm_image_io_wasi/gdcm_read_image.py
itkwasm_image_io_wasi/gdcm_write_image.py
itkwasm_image_io_wasi/ge4_read_image.py
itkwasm_image_io_wasi/ge4_write_image.py
itkwasm_image_io_wasi/ge5_read_image.py
itkwasm_image_io_wasi/ge5_write_image.py
itkwasm_image_io_wasi/ge_adw_read_image.py
itkwasm_image_io_wasi/ge_adw_write_image.py
itkwasm_image_io_wasi/gipl_read_image.py
itkwasm_image_io_wasi/gipl_write_image.py
itkwasm_image_io_wasi/image_io_index.py
itkwasm_image_io_wasi/jpeg_read_image.py
itkwasm_image_io_wasi/jpeg_write_image.py
itkwasm_image_io_wasi/lsm_read_image.py
itkwasm_image_io_wasi/lsm_write_image.py
itkwasm_image_io_wasi/meta_read_image.py
itkwasm_image_io_wasi/meta_write_image.py
itkwasm_image_io_wasi/mgh_read_image.py
itkwasm_image_io_wasi/mgh_write_image.py
itkwasm_image_io_wasi/mrc_read_image.py
itkwasm_image_io_wasi/mrc_write_image.py
itkwasm_image_io_wasi/nifti_read_image.py
itkwasm_image_io_wasi/nifti_write_image.py
itkwasm_image_io_wasi/nrrd_read_image.py
itkwasm_image_io_wasi/nrrd_write_image.py
itkwasm_image_io_wasi/png_read_image.py
itkwasm_image_io_wasi/png_write_image.py
itkwasm_image_io_wasi/read_image.py
itkwasm_image_io_wasi/scanco_read_image.py
itkwasm_image_io_wasi/scanco_write_image.py
itkwasm_image_io_wasi/tiff_read_image.py
itkwasm_image_io_wasi/tiff_write_image.py
itkwasm_image_io_wasi/vtk_read_image.py
itkwasm_image_io_wasi/vtk_write_image.py
itkwasm_image_io_wasi/wasm_read_image.py
itkwasm_image_io_wasi/wasm_write_image.py
itkwasm_image_io_wasi/wasm_zstd_read_image.py
itkwasm_image_io_wasi/wasm_zstd_write_image.py
itkwasm_image_io_wasi/write_image.py
itkwasm_image_io_wasi-1.6.0.dist-info/METADATA
itkwasm_image_io_wasi-1.6.0.dist-info/WHEEL
itkwasm_image_io_wasi-1.6.0.dist-info/RECORD
